dbc_influxdb/__init__.py
dbc_influxdb/common.py
dbc_influxdb/db.py
dbc_influxdb/fluxql.py
dbc_influxdb/main.py
dbc_influxdb/manual_run.py
dbc_influxdb/varscanner.py
dbc_influxdb-0.13.1.dist-info/METADATA
dbc_influxdb-0.13.1.dist-info/WHEEL
dbc_influxdb-0.13.1.dist-info/RECORD
